spi_slave.v
module spi_slave #(parameter DATA_WIDTH = 8)(
    input  wire sclk,        // SPI clock from master
    input  wire rst,         // Reset
    input  wire MOSI,        // Master Out Slave In
    input  wire cs_n,        // Chip Select (active low)
    input  wire [DATA_WIDTH-1:0] TXS_DATA,  // Data to send

    output reg  MISO,        // Master In Slave Out
    output reg  [DATA_WIDTH-1:0] RXS_DATA   // Received data
);

    reg [DATA_WIDTH-1:0] shift_reg_miso;
    reg [DATA_WIDTH-1:0] shift_reg_mosi;
    reg [$clog2(DATA_WIDTH):0] bit_count;

    // Shift in/out data on each SCLK edge
    always @(posedge sclk or posedge rst) begin
        if (rst) begin
            shift_reg_miso <= 0;
            shift_reg_mosi <= 0;
            bit_count      <= 0;
            MISO           <= 0;
            RXS_DATA       <= 0;
        end 
        else if (!cs_n) begin
            // Shift in MOSI
            shift_reg_mosi <= {shift_reg_mosi[DATA_WIDTH-2:0], MOSI};

            // Shift out MISO
            MISO <= shift_reg_miso[DATA_WIDTH-1];
            shift_reg_miso <= {shift_reg_miso[DATA_WIDTH-2:0], 1'b0};

            // Counter
            bit_count <= bit_count + 1;

            // Word received?
            if (bit_count == DATA_WIDTH-1) begin
                RXS_DATA <= shift_reg_mosi;
                bit_count <= 0;
                shift_reg_miso <= TXS_DATA; // load next data
            end
        end else RXS_DATA <= shift_reg_mosi;
    end

    // Load data when CS goes low
    always @(negedge cs_n or posedge rst) begin
        if (rst) begin
            shift_reg_miso <= 0;
        end else begin
            shift_reg_miso <= TXS_DATA;
            bit_count <= 0;
        end
    end
endmodule

spi_master.v
module spi_master #(parameter DATA_WIDTH = 8)(
    input clk, rst,
    input [DATA_WIDTH-1:0]TX_DATA,
    input MISO,
    input tx_start,

    output reg sclk,
    output reg cs_n,
    output reg MOSI,
    output reg [DATA_WIDTH-1:0]RX_DATA //for cpu
);

    reg [DATA_WIDTH-1:0]shift_reg_mosi;
    reg [DATA_WIDTH-1:0]shift_reg_miso;
    reg [$clog2(DATA_WIDTH):0] count;

    parameter IDLE = 0,
              START = 1,
              TRANSFER = 2,
              STOP = 3;

    reg [1:0]state;

    always @(posedge clk) begin
        if(rst) begin
            MOSI <= 0;
            cs_n <= 1;
            sclk <= 0;
            RX_DATA <= 0;
            state <= IDLE;
            count <= DATA_WIDTH;
        end else begin
            case(state)
                IDLE: begin
                    MOSI <= 0;
                    cs_n <= 1;
                    sclk <= 0;
                    count <= DATA_WIDTH;
                    if(tx_start)
                        state <= START;
                end
                START: begin
                    cs_n <= 0;
                    shift_reg_mosi <= TX_DATA;
                    sclk <= 0;
                    state <= TRANSFER;
                end
                TRANSFER: begin
                    //transfering
                    MOSI <= shift_reg_mosi[DATA_WIDTH-1];
                    shift_reg_mosi <= {shift_reg_mosi[DATA_WIDTH-2:0], 1'b0};
                    //receiving
                    shift_reg_miso <= {shift_reg_miso[DATA_WIDTH-2:0], MISO};
                    //counter
                    count <= count - 1;
                    if(count == 1) begin
                        state <= STOP;
                    end else state <= TRANSFER;
                end
                STOP: begin
                    cs_n <= 1;
                    sclk <= 1;
                    RX_DATA <= shift_reg_miso;
                    state <= IDLE;
                end
            endcase
        end
    end

    always @(posedge clk or negedge clk) begin
        if(!cs_n)sclk <= 1;
    end
    always @(negedge clk) begin
        if(!cs_n)sclk <= 0;
    end

endmodule

spi_top.v
`include "spi_master.v"
`include "spi_slave.v"

module spi_top #(parameter DATA_WIDTH = 8)(
    input clk,
    input rst,
    input tx_start,
    input [DATA_WIDTH-1:0] master_tx_data,
    input [DATA_WIDTH-1:0] slave_tx_data,

    output [DATA_WIDTH-1:0] master_rx_data,
    output [DATA_WIDTH-1:0] slave_rx_data
);

    wire sclk, cs_n, MOSI, MISO;

    spi_master #(.DATA_WIDTH(DATA_WIDTH)) master (
        .clk(clk),
        .rst(rst),
        .TX_DATA(master_tx_data),
        .MISO(MISO),
        .tx_start(tx_start),
        .sclk(sclk),
        .cs_n(cs_n),
        .MOSI(MOSI),
        .RX_DATA(master_rx_data)
    );

    spi_slave #(.DATA_WIDTH(DATA_WIDTH)) slave (
        .sclk(sclk),
        .rst(rst),
        .MOSI(MOSI),
        .cs_n(cs_n),
        .TXS_DATA(slave_tx_data),
        .MISO(MISO),
        .RXS_DATA(slave_rx_data)
    );

endmodule

spi_top_tb.v
`timescale 1ns/1ns
`include "spi_top.v"

module spi_top_tb;

    parameter DATA_WIDTH = 8;
    reg clk, rst, tx_start;
    reg [DATA_WIDTH-1:0] master_tx_data, slave_tx_data;
    wire [DATA_WIDTH-1:0] master_rx_data, slave_rx_data;

    spi_top #(.DATA_WIDTH(DATA_WIDTH)) dut (
        .clk(clk),
        .rst(rst),
        .tx_start(tx_start),
        .master_tx_data(master_tx_data),
        .slave_tx_data(slave_tx_data),
        .master_rx_data(master_rx_data),
        .slave_rx_data(slave_rx_data)
    );

    // Clock generation
    initial clk = 0;
    always #5 clk = ~clk; // 100MHz clock

    initial begin
        rst = 1;
        tx_start = 0;
        master_tx_data = 8'hA5;
        slave_tx_data  = 8'h3C;

        #20 rst = 0;
        #10 tx_start = 1;
        #10 tx_start = 0;

        // Wait for transfer to complete
        #200;

        $display("Master received: %h", master_rx_data);
        $display("Slave received:  %h", slave_rx_data);

        $finish;
    end

    initial begin
        $dumpfile("spi_top.vcd");
        $dumpvars(0, spi_top_tb);
    end

endmodule

spi_top.vcd
$date
	Sun Aug 24 21:47:59 2025
$end
$version
	Icarus Verilog
$end
$timescale
	1ns
$end
$scope module spi_top_tb $end
$var wire 8 ! slave_rx_data [7:0] $end
$var wire 8 " master_rx_data [7:0] $end
$var parameter 32 # DATA_WIDTH $end
$var reg 1 $ clk $end
$var reg 8 % master_tx_data [7:0] $end
$var reg 1 & rst $end
$var reg 8 ' slave_tx_data [7:0] $end
$var reg 1 ( tx_start $end
$scope module dut $end
$var wire 1 $ clk $end
$var wire 8 ) master_tx_data [7:0] $end
$var wire 1 & rst $end
$var wire 8 * slave_tx_data [7:0] $end
$var wire 1 ( tx_start $end
$var wire 8 + slave_rx_data [7:0] $end
$var wire 1 , sclk $end
$var wire 8 - master_rx_data [7:0] $end
$var wire 1 . cs_n $end
$var wire 1 / MOSI $end
$var wire 1 0 MISO $end
$var parameter 32 1 DATA_WIDTH $end
$scope module master $end
$var wire 8 2 TX_DATA [7:0] $end
$var wire 1 $ clk $end
$var wire 1 & rst $end
$var wire 1 ( tx_start $end
$var wire 1 0 MISO $end
$var parameter 32 3 DATA_WIDTH $end
$var parameter 32 4 IDLE $end
$var parameter 32 5 START $end
$var parameter 32 6 STOP $end
$var parameter 32 7 TRANSFER $end
$var reg 1 / MOSI $end
$var reg 8 8 RX_DATA [7:0] $end
$var reg 4 9 count [3:0] $end
$var reg 1 . cs_n $end
$var reg 1 , sclk $end
$var reg 8 : shift_reg_miso [7:0] $end
$var reg 8 ; shift_reg_mosi [7:0] $end
$var reg 2 < state [1:0] $end
$upscope $end
$scope module slave $end
$var wire 1 / MOSI $end
$var wire 8 = TXS_DATA [7:0] $end
$var wire 1 . cs_n $end
$var wire 1 & rst $end
$var wire 1 , sclk $end
$var parameter 32 > DATA_WIDTH $end
$var reg 1 0 MISO $end
$var reg 8 ? RXS_DATA [7:0] $end
$var reg 4 @ bit_count [3:0] $end
$var reg 8 A shift_reg_miso [7:0] $end
$var reg 8 B shift_reg_mosi [7:0] $end
$upscope $end
$upscope $end
$upscope $end
$enddefinitions $end
$comment Show the parameter values. $end
$dumpall
b1000 >
b10 7
b11 6
b1 5
b0 4
b1000 3
b1000 1
b1000 #
$end
#0
$dumpvars
b0 B
b0 A
b0 @
b0 ?
b111100 =
bx <
bx ;
bx :
bx 9
bx 8
b10100101 2
00
x/
x.
bx -
x,
b0 +
b111100 *
b10100101 )
0(
b111100 '
1&
b10100101 %
0$
bx "
b0 !
$end
#5
b1000 9
b0 <
b0 "
b0 -
b0 8
0,
1.
0/
1$
#10
0$
#15
1$
#20
0$
0&
#25
1$
#30
0$
1(
#35
b1 <
1$
#40
0$
0(
#45
b111100 A
b10 <
b10100101 ;
0.
1$
#50
b1 @
b1111000 A
0,
0$
#55
b10 @
b11110000 A
b1 B
1,
b111 9
bx0 :
b1001010 ;
1/
1$
#60
0,
0$
#65
b11 @
b11100000 A
10
b10 B
1,
b110 9
bx00 :
b10010100 ;
0/
1$
#70
0,
0$
#75
b100 @
b11000000 A
b101 B
1,
b101 9
bx001 :
b101000 ;
1/
1$
#80
0,
0$
#85
b101 @
b10000000 A
b1010 B
1,
b100 9
bx0011 :
b1010000 ;
0/
1$
#90
0,
0$
#95
b110 @
b0 A
b10100 B
1,
b11 9
bx00111 :
b10100000 ;
1$
#100
0,
0$
#105
b111 @
00
b101001 B
1,
b10 9
bx001111 :
b1000000 ;
1/
1$
#110
0,
0$
#115
b111100 A
b101001 !
b101001 +
b101001 ?
b0 @
b1010010 B
1,
b1 9
bx0011110 :
b10000000 ;
0/
1$
#120
0,
0$
#125
b1 @
b1111000 A
b10100101 B
1,
b11 <
b0 9
b111100 :
b0 ;
1/
1$
#130
0,
0$
#135
b10100101 !
b10100101 +
b10100101 ?
b0 <
b111100 "
b111100 -
b111100 8
1,
1.
1$
#140
0$
#145
b1000 9
0,
0/
1$
